pyripherals/__init__.py
pyripherals/core.py
pyripherals/utils.py
pyripherals/peripherals/AD5453.py
pyripherals/peripherals/AD7961.py
pyripherals/peripherals/ADCDATA.py
pyripherals/peripherals/ADS8686.py
pyripherals/peripherals/DAC101C081.py
pyripherals/peripherals/DAC53401.py
pyripherals/peripherals/DAC80508.py
pyripherals/peripherals/DDR3.py
pyripherals/peripherals/I2CController.py
pyripherals/peripherals/SPIController.py
pyripherals/peripherals/SPIFifoDriven.py
pyripherals/peripherals/TCA9555.py
pyripherals/peripherals/TMF8801.py
pyripherals/peripherals/UID_24AA025UID.py
pyripherals/peripherals/__init__.py
pyripherals-0.0.3.dist-info/LICENSE
pyripherals-0.0.3.dist-info/METADATA
pyripherals-0.0.3.dist-info/WHEEL
pyripherals-0.0.3.dist-info/top_level.txt
pyripherals-0.0.3.dist-info/RECORD
