Metadata-Version: 2.1
Name: pyripherals
Version: 0.0.3
Summary: Python solution for communicating with peripheral ICs
Home-page: https://github.com/Ajstros/pyripherals
Author: Abe Stroschein
Author-email: ajstros@duck.com
Project-URL: Bug Tracker, https://github.com/Ajstros/pyripherals/issues
Classifier: Programming Language :: Python :: 3
Classifier: License :: OSI Approved :: GNU General Public License (GPL)
Classifier: Operating System :: OS Independent
Requires-Python: >=3.6
License-File: LICENSE
Requires-Dist: numpy (>=1.21.1)
Requires-Dist: numfi (>=0.2.4)
Requires-Dist: matplotlib (>=3.5.2)
Requires-Dist: pandas (>=1.3.1)
Requires-Dist: openpyxl (>=3.0.7)
Requires-Dist: h5py (>=3.7.0)
Requires-Dist: PyYAML (>=5.4.1)
Requires-Dist: scipy (>=1.6.3)
